hardest/__init__.py
hardest/detectors.py
hardest/hardness_definitions.py
hardest/hardness_strategies.py
hardest/pseudo_ground_truth_models.py
hardest/pycocotools.py
hardest/utils.py
hardest-0.0.0.dist-info/LICENSE
hardest-0.0.0.dist-info/METADATA
hardest-0.0.0.dist-info/WHEEL
hardest-0.0.0.dist-info/top_level.txt
hardest-0.0.0.dist-info/RECORD
