Metadata-Version: 2.1
Name: hardest
Version: 0.0.0
Summary: The HARDness ESTimation package: ranks an object detection dataset by the expected hardness of the images.
Home-page: 
Author: Jonathan Sadeghi
Author-email: jonathan.sadeghi@five.ai
Classifier: Programming Language :: Python :: 3.9
Classifier: Operating System :: POSIX :: Linux
Requires-Python: >=3.8
License-File: LICENSE
Requires-Dist: torch
Requires-Dist: torchvision
Requires-Dist: torchmetrics
Requires-Dist: scipy
Requires-Dist: sklearn
Requires-Dist: num2words
Requires-Dist: pandas
Requires-Dist: tqdm
Requires-Dist: tueplots
Provides-Extra: test
Requires-Dist: pytest ; extra == 'test'
Requires-Dist: requests ; extra == 'test'
Requires-Dist: pycocotools ; extra == 'test'
